{
  "versao": "V1-prototipo",
  "modelo": "DQN V10 (6 produtos)",
  "gerado_em": "2026-05-11",
  "horizonte_dias": 60,
  "total_campanhas": 9,
  "lucro_adicional_total_estimado_R$": 233.45,
  "limitacoes_conhecidas": [
    "Apenas 6 produtos (faltam chocolate, vinho, snacks, etc.)",
    "Não considera datas comerciais (Dia dos Namorados, Mães, Black Friday)",
    "Elasticidade da literatura, não medida no posto",
    "Estoque simulado, não real",
    "Combo via heurística PARES_COMBO, não validado por análise de cesta"
  ],
  "campanhas": [
    {
      "id": "camp_2026-05-11_agua",
      "data_inicio": "2026-05-11",
      "data_fim": "2026-05-15",
      "duracao_dias": 5,
      "tipo": "combo",
      "produto_principal": "agua",
      "produto_complementar": "energetico",
      "desconto_recomendado_%": 10,
      "uplift_un_principal_estimado": 4.8,
      "uplift_un_complementar_estimado": 1.0,
      "lucro_adicional_estimado_R$": 27.7,
      "fator_demanda_medio": 0.478,
      "dias_semana": [
        "Segunda",
        "Terça",
        "Quarta",
        "Quinta",
        "Sexta"
      ],
      "justificativa": "Período de demanda fraca (fator médio 0.48 × baseline). Combo Água + Energético a -10% deve estimular giro com 9 turnos de oportunidade."
    },
    {
      "id": "camp_2026-05-18_cerveja",
      "data_inicio": "2026-05-18",
      "data_fim": "2026-05-22",
      "duracao_dias": 5,
      "tipo": "combo",
      "produto_principal": "cerveja",
      "produto_complementar": "refrigerante",
      "desconto_recomendado_%": 10,
      "uplift_un_principal_estimado": 2.7,
      "uplift_un_complementar_estimado": 2.0,
      "lucro_adicional_estimado_R$": 21.86,
      "fator_demanda_medio": 0.478,
      "dias_semana": [
        "Segunda",
        "Terça",
        "Quarta",
        "Quinta",
        "Sexta"
      ],
      "justificativa": "Período de demanda fraca (fator médio 0.48 × baseline). Combo Cerveja + Refrigerante a -10% deve estimular giro com 9 turnos de oportunidade."
    },
    {
      "id": "camp_2026-05-25_energetico",
      "data_inicio": "2026-05-25",
      "data_fim": "2026-05-29",
      "duracao_dias": 5,
      "tipo": "combo",
      "produto_principal": "energetico",
      "produto_complementar": "refrigerante",
      "desconto_recomendado_%": 10,
      "uplift_un_principal_estimado": 1.5,
      "uplift_un_complementar_estimado": 2.0,
      "lucro_adicional_estimado_R$": 25.68,
      "fator_demanda_medio": 0.478,
      "dias_semana": [
        "Segunda",
        "Terça",
        "Quarta",
        "Quinta",
        "Sexta"
      ],
      "justificativa": "Período de demanda fraca (fator médio 0.48 × baseline). Combo Energético + Refrigerante a -10% deve estimular giro com 9 turnos de oportunidade."
    },
    {
      "id": "camp_2026-06-01_agua",
      "data_inicio": "2026-06-01",
      "data_fim": "2026-06-05",
      "duracao_dias": 5,
      "tipo": "combo",
      "produto_principal": "agua",
      "produto_complementar": "energetico",
      "desconto_recomendado_%": 10,
      "uplift_un_principal_estimado": 5.5,
      "uplift_un_complementar_estimado": 1.2,
      "lucro_adicional_estimado_R$": 31.68,
      "fator_demanda_medio": 0.546,
      "dias_semana": [
        "Segunda",
        "Terça",
        "Quarta",
        "Quinta",
        "Sexta"
      ],
      "justificativa": "Período de demanda fraca (fator médio 0.55 × baseline). Combo Água + Energético a -10% deve estimular giro com 7 turnos de oportunidade."
    },
    {
      "id": "camp_2026-06-08_cerveja",
      "data_inicio": "2026-06-08",
      "data_fim": "2026-06-12",
      "duracao_dias": 5,
      "tipo": "combo",
      "produto_principal": "cerveja",
      "produto_complementar": "refrigerante",
      "desconto_recomendado_%": 10,
      "uplift_un_principal_estimado": 3.1,
      "uplift_un_complementar_estimado": 2.3,
      "lucro_adicional_estimado_R$": 24.99,
      "fator_demanda_medio": 0.546,
      "dias_semana": [
        "Segunda",
        "Terça",
        "Quarta",
        "Quinta",
        "Sexta"
      ],
      "justificativa": "Período de demanda fraca (fator médio 0.55 × baseline). Combo Cerveja + Refrigerante a -10% deve estimular giro com 7 turnos de oportunidade."
    },
    {
      "id": "camp_2026-06-15_energetico",
      "data_inicio": "2026-06-15",
      "data_fim": "2026-06-19",
      "duracao_dias": 5,
      "tipo": "combo",
      "produto_principal": "energetico",
      "produto_complementar": "refrigerante",
      "desconto_recomendado_%": 10,
      "uplift_un_principal_estimado": 1.7,
      "uplift_un_complementar_estimado": 2.3,
      "lucro_adicional_estimado_R$": 29.37,
      "fator_demanda_medio": 0.546,
      "dias_semana": [
        "Segunda",
        "Terça",
        "Quarta",
        "Quinta",
        "Sexta"
      ],
      "justificativa": "Período de demanda fraca (fator médio 0.55 × baseline). Combo Energético + Refrigerante a -10% deve estimular giro com 7 turnos de oportunidade."
    },
    {
      "id": "camp_2026-06-22_agua",
      "data_inicio": "2026-06-22",
      "data_fim": "2026-06-26",
      "duracao_dias": 5,
      "tipo": "combo",
      "produto_principal": "agua",
      "produto_complementar": "energetico",
      "desconto_recomendado_%": 10,
      "uplift_un_principal_estimado": 5.5,
      "uplift_un_complementar_estimado": 1.2,
      "lucro_adicional_estimado_R$": 31.68,
      "fator_demanda_medio": 0.546,
      "dias_semana": [
        "Segunda",
        "Terça",
        "Quarta",
        "Quinta",
        "Sexta"
      ],
      "justificativa": "Período de demanda fraca (fator médio 0.55 × baseline). Combo Água + Energético a -10% deve estimular giro com 7 turnos de oportunidade."
    },
    {
      "id": "camp_2026-06-29_cerveja",
      "data_inicio": "2026-06-29",
      "data_fim": "2026-07-03",
      "duracao_dias": 5,
      "tipo": "combo",
      "produto_principal": "cerveja",
      "produto_complementar": "refrigerante",
      "desconto_recomendado_%": 10,
      "uplift_un_principal_estimado": 2.7,
      "uplift_un_complementar_estimado": 2.1,
      "lucro_adicional_estimado_R$": 22.15,
      "fator_demanda_medio": 0.484,
      "dias_semana": [
        "Segunda",
        "Terça",
        "Quarta",
        "Quinta",
        "Sexta"
      ],
      "justificativa": "Período de demanda fraca (fator médio 0.48 × baseline). Combo Cerveja + Refrigerante a -10% deve estimular giro com 9 turnos de oportunidade."
    },
    {
      "id": "camp_2026-07-06_energetico",
      "data_inicio": "2026-07-06",
      "data_fim": "2026-07-09",
      "duracao_dias": 4,
      "tipo": "combo",
      "produto_principal": "energetico",
      "produto_complementar": "refrigerante",
      "desconto_recomendado_%": 10,
      "uplift_un_principal_estimado": 1.1,
      "uplift_un_complementar_estimado": 1.5,
      "lucro_adicional_estimado_R$": 18.34,
      "fator_demanda_medio": 0.426,
      "dias_semana": [
        "Segunda",
        "Terça",
        "Quarta",
        "Quinta"
      ],
      "justificativa": "Período de demanda fraca (fator médio 0.43 × baseline). Combo Energético + Refrigerante a -10% deve estimular giro com 8 turnos de oportunidade."
    }
  ]
}